kohilites/VERSION
kohilites/__init__.py
kohilites/cli.py
kohilites/kohilites.py
kohilites/utils.py
kohilites-0.0.1.dist-info/METADATA
kohilites-0.0.1.dist-info/WHEEL
kohilites-0.0.1.dist-info/entry_points.txt
kohilites-0.0.1.dist-info/licenses/LICENSE
kohilites-0.0.1.dist-info/RECORD
