Metadata-Version: 2.1
Name: kohilites
Version: 0.0.1
Summary: A lightweight command line tool to extract and save highlights and notes made on KOReader.
Project-URL: Home, https://github.com/georgerichardson/kohilites
Author-email: George Richardson <georgerichardson@posteo.net>
License: Copyright © 2022 George Richardson, <georgerichardson@posteo.net>
License-File: LICENSE
Classifier: Development Status :: 3 - Alpha
Classifier: Intended Audience :: Developers
Classifier: License :: OSI Approved :: MIT License
Classifier: Natural Language :: English
Classifier: Operating System :: OS Independent
Classifier: Programming Language :: Python :: 3
Requires-Python: >=3.8
Requires-Dist: mdutils>=1.3.1
Requires-Dist: slpp>=1.2.3
Provides-Extra: dev
Requires-Dist: setuptools~=63.2.0; extra == 'dev'
Requires-Dist: wheel~=0.37.1; extra == 'dev'
Provides-Extra: test
Requires-Dist: pytest==7.2.0; extra == 'test'
